CHANGES.txt
MANIFEST.in
README.txt
setup.py
docs/changes.rst
docs/conf.py
docs/globals.rst
docs/index.rst
docs/install.rst
docs/migrate.rst
docs/permissions.rst
docs/pip.rst
docs/server.rst
docs/settings.rst
docs/upload.rst
docs/_ext/djangodocs.py
docs/_static/rdt.css
docs/_theme/wfp/_layout.html
docs/_theme/wfp/conf.py.conf
docs/_theme/wfp/theme.conf
docs/_theme/wfp/_static/rdt.css
pyppi/__init__.py
pyppi/admin.py
pyppi/backends.py
pyppi/feeds.py
pyppi/fields.py
pyppi/forms.py
pyppi/http.py
pyppi/log.py
pyppi/models.py
pyppi/search_indexes.py
pyppi/settings.py
pyppi/storage.py
pyppi/tests.py
pyppi/urls.py
pyppi/util.py
pyppi.egg-info/PKG-INFO
pyppi.egg-info/SOURCES.txt
pyppi.egg-info/dependency_links.txt
pyppi.egg-info/requires.txt
pyppi.egg-info/top_level.txt
pyppi/bin/pyppi
pyppi/fixtures/pyppi_initial.json
pyppi/management/__init__.py
pyppi/management/commands/__init__.py
pyppi/management/commands/init-server.py
pyppi/management/commands/loadclassifiers.py
pyppi/management/commands/ppadd.py
pyppi/management/commands/start.py
pyppi/management/commands/stop.py
pyppi/management/commands/syncpypi.py
pyppi/management/commands/upgrade.py
pyppi/migrations/0001_initial.py
pyppi/migrations/0002_auto__del_field_package_is_protected__del_field_package_is_public__add.py
pyppi/migrations/0003_auto__add_field_package_access.py
pyppi/migrations/0004_auto__del_masterindex__add_mirrorsite__chg_field_mirrorlog_master.py
pyppi/migrations/0005_auto__del_field_mirrorsite_title__add_field_mirrorsite_name__add_field.py
pyppi/migrations/0006_auto__add_accesslogentry__chg_field_release_package_info.py
pyppi/migrations/0007_auto__add_field_accesslogentry_datetime.py
pyppi/migrations/0008_auto__add_field_accesslogentry_traceback__add_field_accesslogentry_mod.py
pyppi/migrations/__init__.py
pyppi/requirements/dev.pip
pyppi/requirements/install.pip
pyppi/requirements/testing.pip
pyppi/server/__init__.py
pyppi/server/requirements.pip
pyppi/server/runner.py
pyppi/server/search_sites.py
pyppi/server/settings.py
pyppi/server/urls.py
pyppi/server/wsgi.py
pyppi/server/fixtures/sax.json
pyppi/templates/403.html
pyppi/templates/404.html
