Metadata-Version: 1.1
Name: pyppi
Version: 0.1.1
Summary: A Django application that emulates the Python Package Index
Home-page: http://github.com/saxix/pyppi
Author: sax
Author-email: s.apostolico@gmail.com
License: BSD
Keywords: django pypi packaging index
Platform: linux
Classifier: Framework :: Django
Classifier: Intended Audience :: Developers
Classifier: Intended Audience :: System Administrators
Classifier: Operating System :: OS Independent
Classifier: Topic :: Software Development
